setup.py
gnb_distributions_gr/Binomialdistribution.py
gnb_distributions_gr/Gaussiandistribution.py
gnb_distributions_gr/Generaldistribution.py
gnb_distributions_gr/__init__.py
gnb_distributions_gr.egg-info/PKG-INFO
gnb_distributions_gr.egg-info/SOURCES.txt
gnb_distributions_gr.egg-info/dependency_links.txt
gnb_distributions_gr.egg-info/not-zip-safe
gnb_distributions_gr.egg-info/top_level.txt