Metadata-Version: 1.0
Name: gnb-distributions-gr
Version: 1.3
Summary: Gaussian and Binomial distributions
Home-page: UNKNOWN
Author: Mustafa Khamisi
Author-email: mustafangure@gmail.com
License: UNKNOWN
Platform: UNKNOWN
